maxcul/__init__.py
maxcul/_communication.py
maxcul/_const.py
maxcul/_exceptions.py
maxcul/_io.py
maxcul/_messages.py
pymaxcul-0.1.12.dist-info/DESCRIPTION.rst
pymaxcul-0.1.12.dist-info/METADATA
pymaxcul-0.1.12.dist-info/RECORD
pymaxcul-0.1.12.dist-info/WHEEL
pymaxcul-0.1.12.dist-info/metadata.json
pymaxcul-0.1.12.dist-info/top_level.txt
