Metadata-Version: 2.0
Name: pymaxcul
Version: 0.1.12
Summary: Talk to eq-3 MAX! devices using a CUL stick
Home-page: https://github.com/maufl/pymaxcul
Author: Markus Ullmann, Karl Wolffgang, Felix Maurer
Author-email: github@maufl.de
License: BSD License
Platform: any
Classifier: Programming Language :: Python
Classifier: Development Status :: 4 - Beta
Classifier: Natural Language :: English
Classifier: Environment :: Console
Classifier: Intended Audience :: Developers
Classifier: License :: OSI Approved :: BSD License
Classifier: Operating System :: OS Independent
Classifier: Topic :: Software Development :: Libraries :: Python Modules
Classifier: Topic :: Home Automation
Provides-Extra: testing
Requires-Dist: pyserial (>=3.1.1)
Provides-Extra: testing
Requires-Dist: pytest; extra == 'testing'
